sunholo/__init__.py
sunholo/custom_logging.py
sunholo/langchain_types.py
sunholo/a2a/__init__.py
sunholo/a2a/agent_card.py
sunholo/a2a/task_manager.py
sunholo/a2a/vac_a2a_agent.py
sunholo/agents/__init__.py
sunholo/agents/chat_history.py
sunholo/agents/dispatch_to_qa.py
sunholo/agents/langserve.py
sunholo/agents/pubsub.py
sunholo/agents/route.py
sunholo/agents/special_commands.py
sunholo/agents/swagger.py
sunholo/agents/fastapi/__init__.py
sunholo/agents/fastapi/base.py
sunholo/agents/fastapi/qna_routes.py
sunholo/agents/fastapi/vac_routes.py
sunholo/agents/flask/__init__.py
sunholo/agents/flask/base.py
sunholo/agents/flask/vac_routes.py
sunholo/archive/__init__.py
sunholo/archive/archive.py
sunholo/auth/__init__.py
sunholo/auth/gcloud.py
sunholo/auth/refresh.py
sunholo/auth/run.py
sunholo/azure/__init__.py
sunholo/azure/auth.py
sunholo/azure/blobs.py
sunholo/azure/event_grid.py
sunholo/bots/__init__.py
sunholo/bots/discord.py
sunholo/bots/github_webhook.py
sunholo/bots/webapp.py
sunholo/chunker/__init__.py
sunholo/chunker/azure.py
sunholo/chunker/doc_handling.py
sunholo/chunker/encode_metadata.py
sunholo/chunker/images.py
sunholo/chunker/loaders.py
sunholo/chunker/message_data.py
sunholo/chunker/pdfs.py
sunholo/chunker/process_chunker_data.py
sunholo/chunker/publish.py
sunholo/chunker/pubsub.py
sunholo/chunker/splitter.py
sunholo/cli/__init__.py
sunholo/cli/chat_vac.py
sunholo/cli/cli.py
sunholo/cli/cli_init.py
sunholo/cli/configs.py
sunholo/cli/deploy.py
sunholo/cli/embedder.py
sunholo/cli/merge_texts.py
sunholo/cli/run_proxy.py
sunholo/cli/sun_rich.py
sunholo/cli/swagger.py
sunholo/cli/vertex.py
sunholo/components/__init__.py
sunholo/components/llm.py
sunholo/components/retriever.py
sunholo/components/vectorstore.py
sunholo/database/__init__.py
sunholo/database/alloydb.py
sunholo/database/alloydb_client.py
sunholo/database/database.py
sunholo/database/lancedb.py
sunholo/database/static_dbs.py
sunholo/database/uuid.py
sunholo/database/sql/sb/create_function.sql
sunholo-0.145.3.dist-info/licenses/LICENSE.txt
sunholo-0.145.3.dist-info/METADATA
sunholo-0.145.3.dist-info/WHEEL
sunholo-0.145.3.dist-info/entry_points.txt
sunholo-0.145.3.dist-info/top_level.txt
sunholo-0.145.3.dist-info/RECORD
